djangorestframework_yaml-1.0.3.dist-info/DESCRIPTION.rst
djangorestframework_yaml-1.0.3.dist-info/METADATA
djangorestframework_yaml-1.0.3.dist-info/metadata.json
djangorestframework_yaml-1.0.3.dist-info/RECORD
djangorestframework_yaml-1.0.3.dist-info/top_level.txt
djangorestframework_yaml-1.0.3.dist-info/WHEEL
rest_framework_yaml/__init__.py
rest_framework_yaml/compat.py
rest_framework_yaml/encoders.py
rest_framework_yaml/parsers.py
rest_framework_yaml/renderers.py
